LICENSE
MANIFEST.in
README.rst
setup.py
django_multisessionform.egg-info/PKG-INFO
django_multisessionform.egg-info/SOURCES.txt
django_multisessionform.egg-info/dependency_links.txt
django_multisessionform.egg-info/requires.txt
django_multisessionform.egg-info/top_level.txt
multisessionform/__init__.py
multisessionform/forms.py
multisessionform/models.py
multisessionform/urls.py
multisessionform/views.py
multisessionform/templatetags/__init__.py
multisessionform/templatetags/multisessionform_tags.py
multisessionform/tests/__init__.py
multisessionform/tests/models.py
multisessionform/tests/tests.py
multisessionform/tests/urls.py