Metadata-Version: 1.1
Name: django-multisessionform
Version: 0.1
Summary: Allows users to complete a ModelForm over multiple sessions"
Home-page: http://github.com/ckirby/django-multisessionform
Author: Chaim Kirby
Author-email: chaimkirby@gmail.com
License: BSD License
Platform: UNKNOWN
Classifier: Environment :: Web Environment
Classifier: Framework :: Django
Classifier: Intended Audience :: Developers
Classifier: License :: OSI Approved :: BSD License
Classifier: Operating System :: OS Independent
Classifier: Programming Language :: Python
Classifier: Programming Language :: Python :: 2.6
Classifier: Programming Language :: Python :: 2.7
Classifier: Topic :: Internet :: WWW/HTTP
Classifier: Topic :: Internet :: WWW/HTTP :: Dynamic Content
